fallthrough_cache
