Metadata-Version: 1.0
Name: django-fallthrough-cache
Version: 0.1.3
Summary: A Django cache backend with fallthrough
Home-page: https://bitbucket.org/dtao/django-fallthrough-cache
Author: Dan Tao
Author-email: daniel.tao@gmail.com
License: MIT
Platform: UNKNOWN
